pyi18n/__init__.py
pyi18n/helpers.py
pyi18n/loaders.py
pyi18n/pyi18n.py
pyi18n/pyi18n_tasks.py
pyi18n/tasks/__init__.py
pyi18n/tasks/normalize.py
tests/__init__.py
tests/helpers.py
tests/run_tests.py
tests/test_helpers.py
tests/test_loaders.py
tests/test_pyi18n.py
tests/test_pyi18n_tasks.py
pyi18n_v2-1.2.2.dist-info/LICENSE
pyi18n_v2-1.2.2.dist-info/METADATA
pyi18n_v2-1.2.2.dist-info/WHEEL
pyi18n_v2-1.2.2.dist-info/entry_points.txt
pyi18n_v2-1.2.2.dist-info/top_level.txt
pyi18n_v2-1.2.2.dist-info/RECORD
