Metadata-Version: 2.1
Name: pyi18n-v2
Version: 1.2.2
Summary: Simple and easy to use internationalizationlibrary inspired by Ruby i18n
Home-page: https://github.com/sectasy0/pyi18n
Author: Piotr Markiewicz
Author-email: sectasy0@gmail.com
License: MIT License
Keywords: pyi18n
Platform: UNKNOWN
Requires-Dist: PyYAML (>=5.4)
